llm_inference_engine/__init__.py
llm_inference_engine/engines.py
llm_inference_engine/llm_configs.py
llm_inference_engine/utils.py
llm_inference_engine-0.1.2.dist-info/METADATA
llm_inference_engine-0.1.2.dist-info/WHEEL
llm_inference_engine-0.1.2.dist-info/RECORD
