Metadata-Version: 2.1
Name: llm-inference-engine
Version: 0.1.2
Summary: LLM inferencing utilities for multiple projects.
License: MIT
Author: Enshuo (David) Hsu
Requires-Python: >=3.11,<4.0
Classifier: License :: OSI Approved :: MIT License
Classifier: Programming Language :: Python :: 3
Classifier: Programming Language :: Python :: 3.11
Classifier: Programming Language :: Python :: 3.12
